{
    "os": "Linux-6.14.0-28-generic-x86_64-with-glibc2.39",
    "python": "3.10.18",
    "heartbeatAt": "2025-08-28T17:59:44.502494",
    "startedAt": "2025-08-28T17:59:43.876756",
    "docker": null,
    "cuda": null,
    "args": [
        "--file_url",
        "https://github.com/udacity/nd0821-c2-build-model-workflow-exercises/blob/master/lesson-2-data-exploration-and-preparation/exercises/exercise_4/starter/genres_mod.parquet?raw=true",
        "--artifact_name",
        "raw_data.parquet",
        "--artifact_type",
        "raw_data",
        "--artifact_description",
        "Data as downloaded"
    ],
    "state": "running",
    "program": "/home/matt-the-ratt/miniconda3/envs/udacity/Udacity-Pipline-Projects/Final-Exercise/genre_classification/starter/download/download_data.py",
    "codePathLocal": "download_data.py",
    "codePath": "starter/download/download_data.py",
    "git": {
        "remote": "https://github.com/MattTheRatt2022/genre_classification.git",
        "commit": "3e8f5c5f7e246fb851df6970df217c348633cda9"
    },
    "email": "matthewzm15@gmail.com",
    "root": "/home/matt-the-ratt/miniconda3/envs/udacity/Udacity-Pipline-Projects/Final-Exercise/genre_classification",
    "host": "Ratts-pc",
    "username": "matt-the-ratt",
    "executable": "/home/matt-the-ratt/miniconda3/envs/mlflow-e190ff1f176d660e6839ac34c7d6bc74393e2ccd/bin/python",
    "cpu_count": 4,
    "cpu_count_logical": 8,
    "cpu_freq": {
        "current": 862.42075,
        "min": 400.0,
        "max": 4700.0
    },
    "cpu_freq_per_core": [
        {
            "current": 400.0,
            "min": 400.0,
            "max": 4700.0
        },
        {
            "current": 399.446,
            "min": 400.0,
            "max": 4700.0
        },
        {
            "current": 503.48,
            "min": 400.0,
            "max": 4700.0
        },
        {
            "current": 1399.683,
            "min": 400.0,
            "max": 4700.0
        },
        {
            "current": 400.0,
            "min": 400.0,
            "max": 4700.0
        },
        {
            "current": 400.625,
            "min": 400.0,
            "max": 4700.0
        },
        {
            "current": 1400.0,
            "min": 400.0,
            "max": 4700.0
        },
        {
            "current": 1400.0,
            "min": 400.0,
            "max": 4700.0
        }
    ],
    "disk": {
        "/": {
            "total": 936.7875633239746,
            "used": 31.848739624023438
        }
    },
    "memory": {
        "total": 15.300792694091797
    }
}
